keytopCache/__init__.py
keytopCache/cache_cluster.py
keytopCache/cache_sentinel.py
keytopCache-1.0.dist-info/LICENSE
keytopCache-1.0.dist-info/METADATA
keytopCache-1.0.dist-info/WHEEL
keytopCache-1.0.dist-info/top_level.txt
keytopCache-1.0.dist-info/RECORD
