Metadata-Version: 2.1
Name: keytopCache
Version: 1.0
Summary: A simple Redis client wrapper for Sentinel and Cluster modes
Home-page: 
Author: zhangjukai
Author-email: zhangjukai@keytop.com.cn
Classifier: Programming Language :: Python :: 3
Classifier: License :: OSI Approved :: MIT License
Classifier: Operating System :: OS Independent
Requires-Python: >=3.6
License-File: LICENSE
Requires-Dist: redis
